PreSynth/iverilog/rtl/register.v
`timescale 1ns / 1ps



module register #(parameter WIDTH_DATA = 8)(
    input [WIDTH_DATA-1:0] datain,
    input clk, enable, reset,
    output reg [WIDTH_DATA-1:0] dataout = 0
    );   
    
    always@(posedge clk, posedge reset)
    begin
    if (reset)
        dataout <= 'b0;
    else 
        if (enable)
            dataout <= datain;
        else dataout <= dataout;
    end
        
endmodule

PreSynth/iverilog/rtl/mac.v
`timescale 1ns / 1ps



module mac #(parameter WIDTH_DATA = 8, parameter N_TAPS = 16, parameter WIDTH_MAC_OUT = 8, parameter WIDTH_COEF0 = 8)(
    input [WIDTH_DATA - 1:0] a,
    input [WIDTH_COEF0 - 1:0]b,
    input reset, clk,
    output reg [WIDTH_MAC_OUT - 1:0] dataout = 0);
    
    reg [WIDTH_MAC_OUT - 1:0] q;
    
    always@(*)begin
        q = dataout + a*b;
    end
    always@(posedge clk)
    begin
    if (reset)
        dataout <= a*b;
    else 
        dataout <= q;
    end
endmodule

PreSynth/iverilog/rtl/retardo.v
`timescale 1ns/1ns

module retardo #(parameter WIDTH = 8, parameter R = 2)(
    input [WIDTH - 1:0] datain,
    input clk, rst, enable,
    output reg [WIDTH - 1:0] dataout);
     
    reg [R:0] i;   
    reg [WIDTH-1:0] rf [R-1:0];

    always @(posedge clk)
    begin
    if (rst) 
	begin
        dataout <= 'b0;
        for(i = 0; i < R; i=i+1)
            rf[i] = 0;
	end
    else 
        if (enable)
            begin
              rf[0] <= datain;
              for(i = 0; i < R-1; i = i+1) begin
                  rf[i+1] <= rf[i];
                  end
              dataout <= rf[R-1];
            end
        else dataout <= 0;
    end
    initial begin
      for(i = 0; i < R; i=i+1)
          rf[i] = 0;
    end
endmodule

rtl/comparador.v
`timescale 1ns / 1ps

module comparador #(parameter LOG2_N_TAPS = 4)(
    input [(LOG2_N_TAPS-1):0] datain,
    input clk, rst,
    output reg dataout
    );
    always@(posedge clk) begin
        if(rst) dataout <= 0;
        else begin 
		if (datain == 0) dataout <= 1;
        	else dataout <= 0; end
    end
endmodule

Qflow/source/rom.v
`timescale 1ns / 1ps



module rom #(parameter WIDTH_COEF0 = 8, parameter N_TAPS = 16, parameter LOG2_N_TAPS = 4)(
    input clk, reset,
    input [LOG2_N_TAPS-1:0] address,
    output reg [WIDTH_COEF0-1:0] data = 0
    );
    
    reg [WIDTH_COEF0-1:0] rom [0:N_TAPS-1];
    
  always @(posedge clk) 
    begin
      if (reset)
          data <= 'b0;
      else 
          data <= rom[address];
      end
    
  initial begin
    $readmemb("rom.mem",rom);
  end
endmodule

Qflow/source/adder.v
`timescale 1ns / 1ps


module adder #(parameter WIDTH_DATA=8)(
    input clk, rst,
    input [WIDTH_DATA-1:0] sum1,
    input [WIDTH_DATA-1:0] sum2,
    output reg [WIDTH_DATA-1:0] res = 0
    );
    
    always@(posedge clk) begin
        if(rst) res <= 0; 
        else res <= sum1 + sum2;
    end
endmodule

PreSynth/iverilog/rtl/asr.v
`timescale 1ns / 1ps

module asr #(parameter WIDTH_DATA = 8, parameter N_TAPS = 16, parameter LOG2_N_TAPS = 4)(
    input clk, reset,
    input [WIDTH_DATA-1:0] q,
    input [LOG2_N_TAPS-1:0] addr,
    input enable,
    output reg [WIDTH_DATA-1:0] dataout = 0,
    output reg [WIDTH_DATA-1:0] en = 0
    );
   
   reg [WIDTH_DATA-1:0] rom [N_TAPS-1:0];
   reg [LOG2_N_TAPS:0] index;
   
   always@(posedge clk, posedge reset)
   begin
   if (reset)
        for(index = 0; index < N_TAPS; index = index + 1) rom[index] <= 0;
   else
       begin
        rom[0] <= q;
        for(index = 1; index < N_TAPS; index = index + 1) rom[index] <= rom[index-1];
       end
   end
   always@(*) begin dataout = rom[addr]; en = rom[N_TAPS-1]; end
   
   initial begin
    for(index = 0; index < N_TAPS; index = index + 1) begin
       rom[index] <= 0;
   end
   end  
endmodule

PreSynth/iverilog/rtl/counter_down.v
`timescale 1ns / 1ps



module counter_down #(parameter LOG2_N_TAPS=8)(
    input reset, clk,
    output reg [(LOG2_N_TAPS-1):0] counter = {LOG2_N_TAPS{1'b1}}
);
initial begin
    counter = {LOG2_N_TAPS{1'b1}};
    end
  always@(posedge clk)
  begin
  if (reset)
    counter = {LOG2_N_TAPS{1'b1}};
  else
    counter = (counter - 1);
  end

endmodule

Qflow/source/counter_up.v
`timescale 1ns / 1ps

 module counter_up #(parameter LOG2_N_TAPS = 4)(
    input reset, clk,
    output reg [(LOG2_N_TAPS-1):0] counter = 0
);
    initial begin
        counter = 0;
        end
      always@(posedge clk)
      begin
      if (reset)
        counter <= 0;
      else
        counter <= (counter + 1);
      end
      
endmodule

Qflow/source/clkdiv.v
`timescale 1ns / 1ps

module clkdiv #(parameter N = 8, parameter LOG2_N = 3)(
    input clkin, reset,
    output reg clkout = 1
    );
    reg [LOG2_N-1:0] div = 0;
    always@(posedge clkin)
    begin
    if (reset) begin div <= 0; clkout <= 1'b1; end
    else begin
        if(div == N-1)
        begin
            clkout <= ~clkout;
            div <= 0;
        end
        else begin clkout <= clkout; div <= div + 1; end
    end
    end
endmodule

Qflow/source/fir2n.v
`timescale 1ns / 1ps

module fir2n #(parameter WIDTH_DATA = 8, parameter N_TAPS = 16, parameter LOG2_N_TAPS = 4, parameter WIDTH_COEF0 = 8, parameter WIDTH_MAC_OUT = 8)(
    input clk, rst,
    input [WIDTH_DATA-1:0] din,
    output [WIDTH_MAC_OUT-1:0] dout
    );
    
    wire clkout;
    wire [WIDTH_DATA-1:0] q;
    wire [WIDTH_DATA-1:0] a;
    wire [WIDTH_DATA-1:0] b;
    wire [(LOG2_N_TAPS-1):0] addr1;
    wire [(LOG2_N_TAPS-1):0] addr2;
    wire [WIDTH_DATA - 1:0] m1;
    wire [WIDTH_COEF0 - 1:0] m2;
    wire r2;
    wire r3;
    wire [WIDTH_MAC_OUT-1:0] q1;
    wire [WIDTH_MAC_OUT-1:0] qfinal;
    wire [WIDTH_DATA - 1:0] aux1;
    wire [WIDTH_DATA - 1:0] nada;
    
    clkdiv #(N_TAPS>>1,3) clk2(.clkin(clk),.clkout(clkout), .reset(rst));
    register #(WIDTH_DATA) reg1(.datain(din), .dataout(q), .reset(rst) ,.clk(clkout), .enable(1'b1));
    counter_up #(LOG2_N_TAPS) counterup(.reset(rst), .clk(clk), .counter(addr1));
    counter_down #(LOG2_N_TAPS) counterdown(.reset(rst), .clk(clk), .counter(addr2));
    asr #(WIDTH_DATA, N_TAPS, LOG2_N_TAPS) asr1(.q(q), .addr(addr1), .clk(clkout), .reset(rst), .enable(1'b1), .dataout(a), .en(aux1));
    asr #(WIDTH_DATA, N_TAPS, LOG2_N_TAPS) asr2(.q(aux1), .addr(addr2), .clk(clkout), .reset(rst), .enable(1'b1), .dataout(b), .en(nada));
    adder #(WIDTH_DATA) sumador(.sum1(a), .sum2(b), .clk(clk), .res(m1), .rst(rst));
    rom #(WIDTH_COEF0, N_TAPS, LOG2_N_TAPS) rom1(.clk(clk), .reset(rst), .address(addr1), .data(m2));
    comparador #(LOG2_N_TAPS) comp(.datain(addr1), .clk(clk), .dataout(r2), .rst(rst));
    retardo #(1, 15) ret2(.datain(r2), .dataout(r3), .clk(clk), .rst(rst), .enable(1'b1));
    mac #(WIDTH_DATA, N_TAPS, WIDTH_MAC_OUT, WIDTH_COEF0) mac1(.a(m1), .b(m2), .reset(r3), .clk(clk), .dataout(q1));
    register #(WIDTH_DATA) reg2(.datain(q1), .dataout(qfinal), .reset(rst) ,.clk(clk), .enable(r3));
    register #(WIDTH_DATA) reg3(.datain(qfinal), .dataout(dout), .reset(rst) ,.clk(clkout), .enable(1'b1));
    

endmodule

PreSynth/iverilog/rtl/fir2n_TB.v
`timescale 1ns / 1ps

module fir2n_TB;

parameter WIDTH_DATA = 8;
parameter WIDTH_COEF0 = 8;
parameter N_TAPS = 16;
parameter LOG2_N_TAPS = 4;
parameter WIDTH_MAC_OUT = 8;

reg clk, rst;
reg [WIDTH_DATA-1:0] din;
wire [WIDTH_MAC_OUT-1:0] dout;
 
fir2n #(.WIDTH_DATA(WIDTH_DATA), .N_TAPS(N_TAPS), .LOG2_N_TAPS(LOG2_N_TAPS), .WIDTH_COEF0(WIDTH_COEF0), .WIDTH_MAC_OUT(WIDTH_MAC_OUT)) uut(.clk(clk), .rst(rst), .din(din), .dout(dout));

initial begin
    $dumpfile("fir2n_TB.vcd");
    $dumpvars(0,fir2n_TB);
    clk = 0;
    rst = 0;
    din = 0;
    #50; rst = 1;
    repeat(100) #10 clk = ~clk;
    rst = 0;
    din = 1;
    repeat(50) #10 clk = ~clk;
    din = 8'b0;
    repeat(1500) #10 clk = ~clk;
    #2000;
    $finish;
end
initial begin
	$monitor("Tiempo: %t \n Datos MAC: \n Adder: %d \n Coef: %d \n Salida MAC: %d \n Salida FIR: %d", $time, uut.m1, uut.m2, uut.q1, uut.dout);
end
endmodule

PreSynth/iverilog/fir2n_TB.vcd
$date
	Sat Jul  6 02:38:28 2019
$end
$version
	Icarus Verilog
$end
$timescale
	1ps
$end
$scope module fir2n_TB $end
$var wire 8 ! dout [7:0] $end
$var reg 1 " clk $end
$var reg 8 # din [7:0] $end
$var reg 1 $ rst $end
$scope module uut $end
$var wire 1 " clk $end
$var wire 8 % din [7:0] $end
$var wire 1 $ rst $end
$var wire 1 & r3 $end
$var wire 1 ' r2 $end
$var wire 8 ( qfinal [7:0] $end
$var wire 8 ) q1 [7:0] $end
$var wire 8 * q [7:0] $end
$var wire 8 + nada [7:0] $end
$var wire 8 , m2 [7:0] $end
$var wire 8 - m1 [7:0] $end
$var wire 8 . dout [7:0] $end
$var wire 1 / clkout $end
$var wire 8 0 b [7:0] $end
$var wire 8 1 aux1 [7:0] $end
$var wire 4 2 addr2 [3:0] $end
$var wire 4 3 addr1 [3:0] $end
$var wire 8 4 a [7:0] $end
$scope module asr1 $end
$var wire 1 5 enable $end
$var wire 1 $ reset $end
$var wire 8 6 q [7:0] $end
$var wire 1 / clk $end
$var wire 4 7 addr [3:0] $end
$var reg 8 8 dataout [7:0] $end
$var reg 8 9 en [7:0] $end
$var reg 5 : index [4:0] $end
$upscope $end
$scope module asr2 $end
$var wire 1 ; enable $end
$var wire 8 < q [7:0] $end
$var wire 1 $ reset $end
$var wire 1 / clk $end
$var wire 4 = addr [3:0] $end
$var reg 8 > dataout [7:0] $end
$var reg 8 ? en [7:0] $end
$var reg 5 @ index [4:0] $end
$upscope $end
$scope module clk2 $end
$var wire 1 " clkin $end
$var wire 1 $ reset $end
$var reg 1 / clkout $end
$var reg 3 A div [2:0] $end
$upscope $end
$scope module comp $end
$var wire 1 " clk $end
$var wire 1 $ rst $end
$var wire 4 B datain [3:0] $end
$var reg 1 ' dataout $end
$upscope $end
$scope module counterdown $end
$var wire 1 " clk $end
$var wire 1 $ reset $end
$var reg 4 C counter [3:0] $end
$upscope $end
$scope module counterup $end
$var wire 1 " clk $end
$var wire 1 $ reset $end
$var reg 4 D counter [3:0] $end
$upscope $end
$scope module mac1 $end
$var wire 1 " clk $end
$var wire 1 & reset $end
$var wire 8 E b [7:0] $end
$var wire 8 F a [7:0] $end
$var reg 8 G dataout [7:0] $end
$var reg 8 H q [7:0] $end
$upscope $end
$scope module reg1 $end
$var wire 1 / clk $end
$var wire 8 I datain [7:0] $end
$var wire 1 J enable $end
$var wire 1 $ reset $end
$var reg 8 K dataout [7:0] $end
$upscope $end
$scope module reg2 $end
$var wire 1 " clk $end
$var wire 8 L datain [7:0] $end
$var wire 1 $ reset $end
$var wire 1 & enable $end
$var reg 8 M dataout [7:0] $end
$upscope $end
$scope module reg3 $end
$var wire 1 / clk $end
$var wire 8 N datain [7:0] $end
$var wire 1 O enable $end
$var wire 1 $ reset $end
$var reg 8 P dataout [7:0] $end
$upscope $end
$scope module ret2 $end
$var wire 1 " clk $end
$var wire 1 ' datain $end
$var wire 1 Q enable $end
$var wire 1 $ rst $end
$var reg 1 & dataout $end
$var reg 16 R i [15:0] $end
$upscope $end
$scope module rom1 $end
$var wire 4 S address [3:0] $end
$var wire 1 " clk $end
$var wire 1 $ reset $end
$var reg 8 T data [7:0] $end
$upscope $end
$scope module sumador $end
$var wire 1 " clk $end
$var wire 1 $ rst $end
$var wire 8 U sum1 [7:0] $end
$var wire 8 V sum2 [7:0] $end
$var reg 8 W res [7:0] $end
$upscope $end
$upscope $end
$upscope $end
$enddefinitions $end
#0
$dumpvars
b0 W
b0 V
b0 U
b0 T
b0 S
b1111 R
1Q
b0 P
1O
b0 N
b0 M
b0 L
b0 K
1J
b0 I
b0 H
b0 G
b0 F
b0 E
b0 D
b1111 C
b0 B
b0 A
b10000 @
b0 ?
b0 >
b1111 =
b0 <
1;
b10000 :
b0 9
b0 8
b0 7
b0 6
15
b0 4
b0 3
b1111 2
b0 1
b0 0
1/
b0 .
b0 -
b0 ,
b0 +
b0 *
b0 )
b0 (
x'
x&
b0 %
0$
b0 #
0"
b0 !
$end
#50000
b10000 :
b10000 @
1$
#60000
0'
0&
b1111 R
1"
#70000
0"
#80000
b1111 R
1"
#90000
0"
#100000
b1111 R
1"
#110000
0"
#120000
b1111 R
1"
#130000
0"
#140000
b1111 R
1"
#150000
0"
#160000
b1111 R
1"
#170000
0"
#180000
b1111 R
1"
#190000
0"
#200000
b1111 R
1"
#210000
0"
#220000
b1111 R
1"
#230000
0"
#240000
b1111 R
1"
#250000
0"
#260000
b1111 R
1"
#270000
0"
#280000
b1111 R
1"
#290000
0"
#300000
b1111 R
1"
#310000
0"
#320000
b1111 R
1"
#330000
0"
#340000
b1111 R
1"
#350000
0"
#360000
b1111 R
1"
#370000
0"
#380000
b1111 R
1"
#390000
0"
#400000
b1111 R
1"
#410000
0"
#420000
b1111 R
1"
#430000
0"
#440000
b1111 R
1"
#450000
0"
#460000
b1111 R
1"
#470000
0"
#480000
b1111 R
1"
#490000
0"
#500000
b1111 R
1"
#510000
0"
#520000
b1111 R
1"
#530000
0"
#540000
b1111 R
1"
#550000
0"
#560000
b1111 R
1"
#570000
0"
#580000
b1111 R
1"
#590000
0"
#600000
b1111 R
1"
#610000
0"
#620000
b1111 R
1"
#630000
0"
#640000
b1111 R
1"
#650000
0"
#660000
b1111 R
1"
#670000
0"
#680000
b1111 R
1"
#690000
0"
#700000
b1111 R
1"
#710000
0"
#720000
b1111 R
1"
#730000
0"
#740000
b1111 R
1"
#750000
0"
#760000
b1111 R
1"
#770000
0"
#780000
b1111 R
1"
#790000
0"
#800000
b1111 R
1"
#810000
0"
#820000
b1111 R
1"
#830000
0"
#840000
b1111 R
1"
#850000
0"
#860000
b1111 R
1"
#870000
0"
#880000
b1111 R
1"
#890000
0"
#900000
b1111 R
1"
#910000
0"
#920000
b1111 R
1"
#930000
0"
#940000
b1111 R
1"
#950000
0"
#960000
b1111 R
1"
#970000
0"
#980000
b1111 R
1"
#990000
0"
#1000000
b1111 R
1"
#1010000
0"
#1020000
b1111 R
1"
#1030000
0"
#1040000
b1111 R
1"
#1050000
b1 #
b1 %
b1 I
0$
0"
#1060000
b1 A
b1 3
b1 7
b1 B
b1 D
b1 S
b1 ,
b1 E
b1 T
1'
b1110 2
b1110 =
b1110 C
b1110 R
1"
#1070000
0"
#1080000
0'
b10 ,
b10 E
b10 T
b10 3
b10 7
b10 B
b10 D
b10 S
b10 A
b1110 R
b1101 2
b1101 =
b1101 C
1"
#1090000
0"
#1100000
b11 A
b11 3
b11 7
b11 B
b11 D
b11 S
b11 ,
b11 E
b11 T
b1100 2
b1100 =
b1100 C
b1110 R
1"
#1110000
0"
#1120000
b100 ,
b100 E
b100 T
b100 3
b100 7
b100 B
b100 D
b100 S
b100 A
b1110 R
b1011 2
b1011 =
b1011 C
1"
#1130000
0"
#1140000
b101 A
b101 3
b101 7
b101 B
b101 D
b101 S
b101 ,
b101 E
b101 T
b1010 2
b1010 =
b1010 C
b1110 R
1"
#1150000
0"
#1160000
b110 ,
b110 E
b110 T
b110 3
b110 7
b110 B
b110 D
b110 S
b110 A
b1110 R
b1001 2
b1001 =
b1001 C
1"
#1170000
0"
#1180000
b111 A
b111 3
b111 7
b111 B
b111 D
b111 S
b111 ,
b111 E
b111 T
b1000 2
b1000 =
b1000 C
b1110 R
1"
#1190000
0"
#1200000
b1000 ,
b1000 E
b1000 T
b1000 3
b1000 7
b1000 B
b1000 D
b1000 S
b0 A
0/
b1110 R
b111 2
b111 =
b111 C
1"
#1210000
0"
#1220000
b1 A
b1001 3
b1001 7
b1001 B
b1001 D
b1001 S
b1001 ,
b1001 E
b1001 T
b110 2
b110 =
b110 C
b1110 R
1"
#1230000
0"
#1240000
b1010 ,
b1010 E
b1010 T
b1010 3
b1010 7
b1010 B
b1010 D
b1010 S
b10 A
b1110 R
b101 2
b101 =
b101 C
1"
#1250000
0"
#1260000
b11 A
b1011 3
b1011 7
b1011 B
b1011 D
b1011 S
b1011 ,
b1011 E
b1011 T
b100 2
b100 =
b100 C
b1110 R
1"
#1270000
0"
#1280000
b1100 ,
b1100 E
b1100 T
b1100 3
b1100 7
b1100 B
b1100 D
b1100 S
b100 A
b1110 R
b11 2
b11 =
b11 C
1"
#1290000
0"
#1300000
b101 A
b1101 3
b1101 7
b1101 B
b1101 D
b1101 S
b1101 ,
b1101 E
b1101 T
b10 2
b10 =
b10 C
b1110 R
1"
#1310000
0"
#1320000
b1110 ,
b1110 E
b1110 T
b1110 3
b1110 7
b1110 B
b1110 D
b1110 S
b110 A
b1110 R
b1 2
b1 =
b1 C
1"
#1330000
0"
#1340000
b111 A
b1111 3
b1111 7
b1111 B
b1111 D
b1111 S
b1111 ,
b1111 E
b1111 T
b0 2
b0 =
b0 C
b1110 R
1"
#1350000
0"
#1360000
b1 *
b1 6
b1 K
b10000 @
b10000 :
b10000 ,
b10000 E
b10000 T
b0 3
b0 7
b0 B
b0 D
b0 S
b0 A
1/
b1110 R
b1111 2
b1111 =
b1111 C
1"
#1370000
0"
#1380000
b1 A
b1 3
b1 7
b1 B
b1 D
b1 S
b1 ,
b1 E
b1 T
1'
1&
b1110 2
b1110 =
b1110 C
b1110 R
1"
#1390000
0"
#1400000
0&
0'
b10 ,
b10 E
b10 T
b10 3
b10 7
b10 B
b10 D
b10 S
b10 A
b1110 R
b1101 2
b1101 =
b1101 C
1"
#1410000
0"
#1420000
b11 A
b11 3
b11 7
b11 B
b11 D
b11 S
b11 ,
b11 E
b11 T
b1100 2
b1100 =
b1100 C
b1110 R
1"
#1430000
0"
#1440000
b100 ,
b100 E
b100 T
b100 3
b100 7
b100 B
b100 D
b100 S
b100 A
b1110 R
b1011 2
b1011 =
b1011 C
1"
#1450000
0"
#1460000
b101 A
b101 3
b101 7
b101 B
b101 D
b101 S
b101 ,
b101 E
b101 T
b1010 2
b1010 =
b1010 C
b1110 R
1"
#1470000
0"
#1480000
b110 ,
b110 E
b110 T
b110 3
b110 7
b110 B
b110 D
b110 S
b110 A
b1110 R
b1001 2
b1001 =
b1001 C
1"
#1490000
0"
#1500000
b111 A
b111 3
b111 7
b111 B
b111 D
b111 S
b111 ,
b111 E
b111 T
b1000 2
b1000 =
b1000 C
b1110 R
1"
#1510000
0"
#1520000
b1000 ,
b1000 E
b1000 T
b1000 3
b1000 7
b1000 B
b1000 D
b1000 S
b0 A
0/
b1110 R
b111 2
b111 =
b111 C
1"
#1530000
0"
#1540000
b1 A
b1001 3
b1001 7
b1001 B
b1001 D
b1001 S
b1001 ,
b1001 E
b1001 T
b110 2
b110 =
b110 C
b1110 R
1"
#1550000
b0 #
b0 %
b0 I
0"
#1560000
b1010 ,
b1010 E
b1010 T
b1010 3
b1010 7
b1010 B
b1010 D
b1010 S
b10 A
b1110 R
b101 2
b101 =
b101 C
1"
#1570000
0"
#1580000
b11 A
b1011 3
b1011 7
b1011 B
b1011 D
b1011 S
b1011 ,
b1011 E
b1011 T
b100 2
b100 =
b100 C
b1110 R
1"
#1590000
0"
#1600000
b1100 ,
b1100 E
b1100 T
b1100 3
b1100 7
b1100 B
b1100 D
b1100 S
b100 A
b1110 R
b11 2
b11 =
b11 C
1"
#1610000
0"
#1620000
b101 A
b1101 3
b1101 7
b1101 B
b1101 D
b1101 S
b1101 ,
b1101 E
b1101 T
b10 2
b10 =
b10 C
b1110 R
1"
#1630000
0"
#1640000
b1110 ,
b1110 E
b1110 T
b1110 3
b1110 7
b1110 B
b1110 D
b1110 S
b110 A
b1110 R
b1 2
b1 =
b1 C
1"
#1650000
0"
#1660000
b111 A
b1111 3
b1111 7
b1111 B
b1111 D
b1111 S
b1111 ,
b1111 E
b1111 T
b0 2
b0 =
b0 C
b1110 R
1"
#1670000
0"
#1680000
b1 4
b1 8
b1 U
b0 *
b0 6
b0 K
b10000 :
b10000 @
b10000 ,
b10000 E
b10000 T
b0 3
b0 7
b0 B
b0 D
b0 S
b0 A
1/
b1110 R
b1111 2
b1111 =
b1111 C
1"
#1690000
0"
#1700000
b0 4
b0 8
b0 U
b1 H
b1 A
b1 3
b1 7
b1 B
b1 D
b1 S
b1 -
b1 F
b1 W
b1 ,
b1 E
b1 T
1'
1&
b1110 2
b1110 =
b1110 C
b1110 R
1"
#1710000
0"
#1720000
b1 )
b1 G
b1 L
0&
0'
b10 ,
b10 E
b10 T
b0 -
b0 F
b0 W
b10 3
b10 7
b10 B
b10 D
b10 S
b10 A
b1110 R
b1101 2
b1101 =
b1101 C
1"
#1730000
0"
#1740000
b11 A
b11 3
b11 7
b11 B
b11 D
b11 S
b11 ,
b11 E
b11 T
b1100 2
b1100 =
b1100 C
b1110 R
1"
#1750000
0"
#1760000
b100 ,
b100 E
b100 T
b100 3
b100 7
b100 B
b100 D
b100 S
b100 A
b1110 R
b1011 2
b1011 =
b1011 C
1"
#1770000
0"
#1780000
b101 A
b101 3
b101 7
b101 B
b101 D
b101 S
b101 ,
b101 E
b101 T
b1010 2
b1010 =
b1010 C
b1110 R
1"
#1790000
0"
#1800000
b110 ,
b110 E
b110 T
b110 3
b110 7
b110 B
b110 D
b110 S
b110 A
b1110 R
b1001 2
b1001 =
b1001 C
1"
#1810000
0"
#1820000
b111 A
b111 3
b111 7
b111 B
b111 D
b111 S
b111 ,
b111 E
b111 T
b1000 2
b1000 =
b1000 C
b1110 R
1"
#1830000
0"
#1840000
b1000 ,
b1000 E
b1000 T
b1000 3
b1000 7
b1000 B
b1000 D
b1000 S
b0 A
0/
b1110 R
b111 2
b111 =
b111 C
1"
#1850000
0"
#1860000
b1 A
b1001 3
b1001 7
b1001 B
b1001 D
b1001 S
b1001 ,
b1001 E
b1001 T
b110 2
b110 =
b110 C
b1110 R
1"
#1870000
0"
#1880000
b1010 ,
b1010 E
b1010 T
b1010 3
b1010 7
b1010 B
b1010 D
b1010 S
b10 A
b1110 R
b101 2
b101 =
b101 C
1"
#1890000
0"
#1900000
b11 A
b1011 3
b1011 7
b1011 B
b1011 D
b1011 S
b1011 ,
b1011 E
b1011 T
b100 2
b100 =
b100 C
b1110 R
1"
#1910000
0"
#1920000
b1100 ,
b1100 E
b1100 T
b1100 3
b1100 7
b1100 B
b1100 D
b1100 S
b100 A
b1110 R
b11 2
b11 =
b11 C
1"
#1930000
0"
#1940000
b101 A
b1101 3
b1101 7
b1101 B
b1101 D
b1101 S
b1101 ,
b1101 E
b1101 T
b10 2
b10 =
b10 C
b1110 R
1"
#1950000
0"
#1960000
b1110 ,
b1110 E
b1110 T
b1110 3
b1110 7
b1110 B
b1110 D
b1110 S
b110 A
b1110 R
b1 2
b1 =
b1 C
1"
#1970000
0"
#1980000
b111 A
b1111 3
b1111 7
b1111 B
b1111 D
b1111 S
b1111 ,
b1111 E
b1111 T
b0 2
b0 =
b0 C
b1110 R
1"
#1990000
0"
#2000000
b0 4
b0 8
b0 U
b10000 @
b10000 :
b10000 ,
b10000 E
b10000 T
b0 3
b0 7
b0 B
b0 D
b0 S
b0 A
1/
b1110 R
b1111 2
b1111 =
b1111 C
1"
#2010000
0"
#2020000
b1 4
b1 8
b1 U
b1 A
b1 3
b1 7
b1 B
b1 D
b1 S
b1 ,
b1 E
b1 T
1'
1&
b1110 2
b1110 =
b1110 C
b1110 R
1"
#2030000
0"
#2040000
b10 H
b0 4
b0 8
b0 U
b0 )
b0 G
b0 L
0&
0'
b10 ,
b10 E
b10 T
b1 -
b1 F
b1 W
b10 3
b10 7
b10 B
b10 D
b10 S
b10 A
b1 (
b1 M
b1 N
b1110 R
b1101 2
b1101 =
b1101 C
1"
#2050000
0"
#2060000
b11 A
b11 3
b11 7
b11 B
b11 D
b11 S
b0 -
b0 F
b0 W
b11 ,
b11 E
b11 T
b10 )
b10 G
b10 L
b1100 2
b1100 =
b1100 C
b1110 R
1"
#2070000
0"
#2080000
b100 ,
b100 E
b100 T
b100 3
b100 7
b100 B
b100 D
b100 S
b100 A
b1110 R
b1011 2
b1011 =
b1011 C
1"
#2090000
0"
#2100000
b101 A
b101 3
b101 7
b101 B
b101 D
b101 S
b101 ,
b101 E
b101 T
b1010 2
b1010 =
b1010 C
b1110 R
1"
#2110000
0"
#2120000
b110 ,
b110 E
b110 T
b110 3
b110 7
b110 B
b110 D
b110 S
b110 A
b1110 R
b1001 2
b1001 =
b1001 C
1"
#2130000
0"
#2140000
b111 A
b111 3
b111 7
b111 B
b111 D
b111 S
b111 ,
b111 E
b111 T
b1000 2
b1000 =
b1000 C
b1110 R
1"
#2150000
0"
#2160000
b1000 ,
b1000 E
b1000 T
b1000 3
b1000 7
b1000 B
b1000 D
b1000 S
b0 A
0/
b1110 R
b111 2
b111 =
b111 C
1"
#2170000
0"
#2180000
b1 A
b1001 3
b1001 7
b1001 B
b1001 D
b1001 S
b1001 ,
b1001 E
b1001 T
b110 2
b110 =
b110 C
b1110 R
1"
#2190000
0"
#2200000
b1010 ,
b1010 E
b1010 T
b1010 3
b1010 7
b1010 B
b1010 D
b1010 S
b10 A
b1110 R
b101 2
b101 =
b101 C
1"
#2210000
0"
#2220000
b11 A
b1011 3
b1011 7
b1011 B
b1011 D
b1011 S
b1011 ,
b1011 E
b1011 T
b100 2
b100 =
b100 C
b1110 R
1"
#2230000
0"
#2240000
b1100 ,
b1100 E
b1100 T
b1100 3
b1100 7
b1100 B
b1100 D
b1100 S
b100 A
b1110 R
b11 2
b11 =
b11 C
1"
#2250000
0"
#2260000
b101 A
b1101 3
b1101 7
b1101 B
b1101 D
b1101 S
b1101 ,
b1101 E
b1101 T
b10 2
b10 =
b10 C
b1110 R
1"
#2270000
0"
#2280000
b1110 ,
b1110 E
b1110 T
b1110 3
b1110 7
b1110 B
b1110 D
b1110 S
b110 A
b1110 R
b1 2
b1 =
b1 C
1"
#2290000
0"
#2300000
b111 A
b1111 3
b1111 7
b1111 B
b1111 D
b1111 S
b1111 ,
b1111 E
b1111 T
b0 2
b0 =
b0 C
b1110 R
1"
#2310000
0"
#2320000
b1 !
b1 .
b1 P
b10000 :
b10000 @
b10000 ,
b10000 E
b10000 T
b0 3
b0 7
b0 B
b0 D
b0 S
b0 A
1/
b1110 R
b1111 2
b1111 =
b1111 C
1"
#2330000
0"
#2340000
b1 A
b1 3
b1 7
b1 B
b1 D
b1 S
b1 ,
b1 E
b1 T
1'
1&
b1110 2
b1110 =
b1110 C
b1110 R
1"
#2350000
0"
#2360000
b0 H
b1 4
b1 8
b1 U
b0 )
b0 G
b0 L
0&
0'
b10 ,
b10 E
b10 T
b10 3
b10 7
b10 B
b10 D
b10 S
b10 A
b10 (
b10 M
b10 N
b1110 R
b1101 2
b1101 =
b1101 C
1"
#2370000
0"
#2380000
b0 4
b0 8
b0 U
b11 H
b11 A
b11 3
b11 7
b11 B
b11 D
b11 S
b1 -
b1 F
b1 W
b11 ,
b11 E
b11 T
b1100 2
b1100 =
b1100 C
b1110 R
1"
#2390000
0"
#2400000
b11 )
b11 G
b11 L
b100 ,
b100 E
b100 T
b0 -
b0 F
b0 W
b100 3
b100 7
b100 B
b100 D
b100 S
b100 A
b1110 R
b1011 2
b1011 =
b1011 C
1"
#2410000
0"
#2420000
b101 A
b101 3
b101 7
b101 B
b101 D
b101 S
b101 ,
b101 E
b101 T
b1010 2
b1010 =
b1010 C
b1110 R
1"
#2430000
0"
#2440000
b110 ,
b110 E
b110 T
b110 3
b110 7
b110 B
b110 D
b110 S
b110 A
b1110 R
b1001 2
b1001 =
b1001 C
1"
#2450000
0"
#2460000
b111 A
b111 3
b111 7
b111 B
b111 D
b111 S
b111 ,
b111 E
b111 T
b1000 2
b1000 =
b1000 C
b1110 R
1"
#2470000
0"
#2480000
b1000 ,
b1000 E
b1000 T
b1000 3
b1000 7
b1000 B
b1000 D
b1000 S
b0 A
0/
b1110 R
b111 2
b111 =
b111 C
1"
#2490000
0"
#2500000
b1 A
b1001 3
b1001 7
b1001 B
b1001 D
b1001 S
b1001 ,
b1001 E
b1001 T
b110 2
b110 =
b110 C
b1110 R
1"
#2510000
0"
#2520000
b1010 ,
b1010 E
b1010 T
b1010 3
b1010 7
b1010 B
b1010 D
b1010 S
b10 A
b1110 R
b101 2
b101 =
b101 C
1"
#2530000
0"
#2540000
b11 A
b1011 3
b1011 7
b1011 B
b1011 D
b1011 S
b1011 ,
b1011 E
b1011 T
b100 2
b100 =
b100 C
b1110 R
1"
#2550000
0"
#2560000
b1100 ,
b1100 E
b1100 T
b1100 3
b1100 7
b1100 B
b1100 D
b1100 S
b100 A
b1110 R
b11 2
b11 =
b11 C
1"
#2570000
0"
#2580000
b101 A
b1101 3
b1101 7
b1101 B
b1101 D
b1101 S
b1101 ,
b1101 E
b1101 T
b10 2
b10 =
b10 C
b1110 R
1"
#2590000
0"
#2600000
b1110 ,
b1110 E
b1110 T
b1110 3
b1110 7
b1110 B
b1110 D
b1110 S
b110 A
b1110 R
b1 2
b1 =
b1 C
1"
